setup.py
porc/__init__.py
porc/client.py
porc/pages.py
porc/patch.py
porc/resource.py
porc/response.py
porc/search.py
porc/util.py
porc/version.py
porc.egg-info/PKG-INFO
porc.egg-info/SOURCES.txt
porc.egg-info/dependency_links.txt
porc.egg-info/requires.txt
porc.egg-info/top_level.txt