Metadata-Version: 1.1
Name: porc
Version: 0.5.1
Summary: Asynchronous Orchestrate.io Interface
Home-page: https://github.com/orchestrate-io/porc
Author: Max Thayer
Author-email: max@orchestrate.io
License: ASLv2
Platform: UNKNOWN
Classifier: Intended Audience :: Developers
Classifier: Natural Language :: English
Classifier: License :: OSI Approved :: Apache Software License
Classifier: Programming Language :: Python
Classifier: Programming Language :: Python :: 2
Classifier: Programming Language :: Python :: 2.7
Classifier: Programming Language :: Python :: 3
Classifier: Programming Language :: Python :: 3.3
Classifier: Programming Language :: Python :: 3.4
